medical_article_sdk/__init__.py
medical_article_sdk/config.json
medical_article_sdk/medical_article_sdk.py
medical_article_sdk/medical_prompt.txt
medical_article_sdk/title_note_prompt.txt
medical_article_sdk/__pycache__/__init__.cpython-312.pyc
medical_article_sdk/__pycache__/medical_article_sdk.cpython-312.pyc
medical_article_sdk-0.1.5.dist-info/METADATA
medical_article_sdk-0.1.5.dist-info/WHEEL
medical_article_sdk-0.1.5.dist-info/top_level.txt
medical_article_sdk-0.1.5.dist-info/RECORD
