Metadata-Version: 2.1
Name: medical_article_sdk
Version: 0.1.5
Summary: A package for correcting medical subtitles
Author: imuzhangy
Author-email: imuzhangying@gmail.com
Classifier: Programming Language :: Python :: 3
Classifier: License :: OSI Approved :: MIT License
Classifier: Operating System :: OS Independent
Requires-Python: >=3.8
Requires-Dist: requests
Requires-Dist: python-docx
